{"frames": [

{
	"filename": "Button_009",
	"frame": {"x":292,"y":2,"w":128,"h":128},
	"rotated": false,
	"trimmed": false,
	"spriteSourceSize": {"x":0,"y":0,"w":128,"h":128},
	"sourceSize": {"w":128,"h":128}
},
{
	"filename": "Button_010",
	"frame": {"x":425,"y":2,"w":128,"h":128},
	"rotated": false,
	"trimmed": false,
	"spriteSourceSize": {"x":0,"y":0,"w":128,"h":128},
	"sourceSize": {"w":128,"h":128}
},
{
	"filename": "Button_011",
	"frame": {"x":558,"y":2,"w":128,"h":128},
	"rotated": false,
	"trimmed": false,
	"spriteSourceSize": {"x":0,"y":0,"w":128,"h":128},
	"sourceSize": {"w":128,"h":128}
},
{
	"filename": "Button_013",
	"frame": {"x":691,"y":2,"w":128,"h":128},
	"rotated": false,
	"trimmed": false,
	"spriteSourceSize": {"x":0,"y":0,"w":128,"h":128},
	"sourceSize": {"w":128,"h":128}
},
{
	"filename": "Button_014",
	"frame": {"x":824,"y":2,"w":128,"h":128},
	"rotated": false,
	"trimmed": false,
	"spriteSourceSize": {"x":0,"y":0,"w":128,"h":128},
	"sourceSize": {"w":128,"h":128}
},
{
	"filename": "Button_015",
	"frame": {"x":292,"y":135,"w":128,"h":128},
	"rotated": false,
	"trimmed": false,
	"spriteSourceSize": {"x":0,"y":0,"w":128,"h":128},
	"sourceSize": {"w":128,"h":128}
},
{
	"filename": "Button_021",
	"frame": {"x":2,"y":209,"w":128,"h":128},
	"rotated": false,
	"trimmed": false,
	"spriteSourceSize": {"x":0,"y":0,"w":128,"h":128},
	"sourceSize": {"w":128,"h":128}
},
{
	"filename": "Button_022",
	"frame": {"x":135,"y":209,"w":128,"h":128},
	"rotated": false,
	"trimmed": false,
	"spriteSourceSize": {"x":0,"y":0,"w":128,"h":128},
	"sourceSize": {"w":128,"h":128}
},
{
	"filename": "Button_023",
	"frame": {"x":425,"y":135,"w":128,"h":128},
	"rotated": false,
	"trimmed": false,
	"spriteSourceSize": {"x":0,"y":0,"w":128,"h":128},
	"sourceSize": {"w":128,"h":128}
},
{
	"filename": "Button_024",
	"frame": {"x":558,"y":135,"w":128,"h":128},
	"rotated": false,
	"trimmed": false,
	"spriteSourceSize": {"x":0,"y":0,"w":128,"h":128},
	"sourceSize": {"w":128,"h":128}
},
{
	"filename": "Button_057",
	"frame": {"x":691,"y":135,"w":128,"h":128},
	"rotated": false,
	"trimmed": false,
	"spriteSourceSize": {"x":0,"y":0,"w":128,"h":128},
	"sourceSize": {"w":128,"h":128}
},
{
	"filename": "Button_058",
	"frame": {"x":824,"y":135,"w":128,"h":128},
	"rotated": false,
	"trimmed": false,
	"spriteSourceSize": {"x":0,"y":0,"w":128,"h":128},
	"sourceSize": {"w":128,"h":128}
},
{
	"filename": "Button_059",
	"frame": {"x":2,"y":342,"w":128,"h":128},
	"rotated": false,
	"trimmed": false,
	"spriteSourceSize": {"x":0,"y":0,"w":128,"h":128},
	"sourceSize": {"w":128,"h":128}
},
{
	"filename": "Button_060",
	"frame": {"x":2,"y":475,"w":128,"h":128},
	"rotated": false,
	"trimmed": false,
	"spriteSourceSize": {"x":0,"y":0,"w":128,"h":128},
	"sourceSize": {"w":128,"h":128}
},
{
	"filename": "Button_093",
	"frame": {"x":2,"y":608,"w":128,"h":128},
	"rotated": false,
	"trimmed": false,
	"spriteSourceSize": {"x":0,"y":0,"w":128,"h":128},
	"sourceSize": {"w":128,"h":128}
},
{
	"filename": "Button_094",
	"frame": {"x":2,"y":741,"w":128,"h":128},
	"rotated": false,
	"trimmed": false,
	"spriteSourceSize": {"x":0,"y":0,"w":128,"h":128},
	"sourceSize": {"w":128,"h":128}
},
{
	"filename": "Button_095",
	"frame": {"x":2,"y":874,"w":128,"h":128},
	"rotated": false,
	"trimmed": false,
	"spriteSourceSize": {"x":0,"y":0,"w":128,"h":128},
	"sourceSize": {"w":128,"h":128}
},
{
	"filename": "Button_121",
	"frame": {"x":135,"y":342,"w":128,"h":128},
	"rotated": false,
	"trimmed": false,
	"spriteSourceSize": {"x":0,"y":0,"w":128,"h":128},
	"sourceSize": {"w":128,"h":128}
},
{
	"filename": "Button_122",
	"frame": {"x":135,"y":475,"w":128,"h":128},
	"rotated": false,
	"trimmed": false,
	"spriteSourceSize": {"x":0,"y":0,"w":128,"h":128},
	"sourceSize": {"w":128,"h":128}
},
{
	"filename": "Button_123",
	"frame": {"x":135,"y":608,"w":128,"h":128},
	"rotated": false,
	"trimmed": false,
	"spriteSourceSize": {"x":0,"y":0,"w":128,"h":128},
	"sourceSize": {"w":128,"h":128}
},
{
	"filename": "youtube-like-start-icon",
	"frame": {"x":2,"y":2,"w":285,"h":202},
	"rotated": false,
	"trimmed": true,
	"spriteSourceSize": {"x":3,"y":3,"w":285,"h":202},
	"sourceSize": {"w":291,"h":208}
}],
"meta": {
	"app": "http://www.codeandweb.com/texturepacker",
	"version": "1.0",
	"image": "game.png",
	"format": "RGBA8888",
	"size": {"w":1024,"h":1024},
	"scale": "1",
	"smartupdate": "$TexturePacker:SmartUpdate:4f9d0a3ee9eb6f2310f7e485ae09a46e:bb631c7bcc7861c3f3d889b9ba1fb7fc:fc2835210f98bae8e8c1b7f0a84c9321$"
}
}
